{
    "gerado_em": "2026-06-25T22:28:46+00:00",
    "modulos": {
        "perguntas": {
            "versao": 1782426526,
            "registros": 1000
        },
        "poesias": {
            "versao": 1782426526,
            "registros": 3
        },
        "receitas": {
            "versao": 1782426526,
            "registros": 12
        },
        "kits": {
            "versao": 1782426526,
            "registros": 12
        },
        "guias": {
            "versao": 1782426526,
            "registros": 18
        },
        "niveis": {
            "versao": 1782426526,
            "registros": 50
        },
        "vibes": {
            "versao": 1782426526,
            "registros": 100
        },
        "criacao_modulos": {
            "versao": 1782426526,
            "registros": 24
        },
        "categorias": {
            "versao": 1782426526,
            "registros": 16
        },
        "anotacao_modelos": {
            "versao": 1782426526,
            "registros": 7
        }
    }
}