[
    {
        "id": 13,
        "id_remoto": null,
        "titulo": "Soro Caseiro de Reidratação",
        "categoria": "🧃",
        "ingredientes": "<ul><li>1 litro de água potável (fervida ou tratada)</li><li>1 colher (chá) rasa de sal</li><li>4 colheres (chá) de açúcar</li></ul>",
        "instrucoes": "<ol><li>Dissolva bem o sal e o açúcar na água tratada.</li><li>Prove: deve ficar menos salgado que uma lágrima.</li><li>Ofereça aos poucos a quem estiver com diarreia ou desidratação.</li><li>Prepare uma solução nova a cada 24 horas e mantenha tampada.</li></ol>",
        "publicar": 1,
        "data_criacao": 1782247889803,
        "data_atualizacao": 1782247889803,
        "e_favorito": 0
    },
    {
        "id": 14,
        "id_remoto": null,
        "titulo": "Salada de Atum de Emergência",
        "categoria": "🥫",
        "ingredientes": "<ul><li>1 lata de atum (em água ou óleo)</li><li>1 lata de grão-de-bico ou milho, escorrida</li><li>1 colher (sopa) de maionese ou azeite</li><li>Sal e suco de limão a gosto (se houver)</li></ul>",
        "instrucoes": "<ol><li>Escorra o atum e o grão-de-bico.</li><li>Misture tudo em uma tigela com a maionese ou o azeite.</li><li>Tempere a gosto e sirva com bolachas ou pão.</li><li>Não precisa de fogo nem de geladeira para o consumo imediato.</li></ol>",
        "publicar": 1,
        "data_criacao": 1782247889803,
        "data_atualizacao": 1782247889803,
        "e_favorito": 0
    },
    {
        "id": 15,
        "id_remoto": null,
        "titulo": "Mingau de Aveia sem Fogo",
        "categoria": "🥣",
        "ingredientes": "<ul><li>4 colheres (sopa) de aveia em flocos</li><li>1 xícara de leite (ou água com leite em pó)</li><li>1 colher (sopa) de açúcar, mel ou passas</li><li>Canela em pó a gosto (opcional)</li></ul>",
        "instrucoes": "<ol><li>Misture a aveia com o leite em um pote com tampa.</li><li>Deixe descansar de 15 minutos a uma noite para amolecer.</li><li>Adoce e finalize com canela ou frutas secas.</li><li>Pronto para comer sem precisar cozinhar.</li></ol>",
        "publicar": 1,
        "data_criacao": 1782247889803,
        "data_atualizacao": 1782247889803,
        "e_favorito": 0
    },
    {
        "id": 16,
        "id_remoto": null,
        "titulo": "Pão de Frigideira sem Fermento",
        "categoria": "🫓",
        "ingredientes": "<ul><li>2 xícaras de farinha de trigo</li><li>3/4 de xícara de água</li><li>1 colher (sopa) de óleo</li><li>1 colher (chá) de sal</li></ul>",
        "instrucoes": "<ol><li>Misture a farinha com o sal e adicione a água e o óleo aos poucos.</li><li>Sove até obter uma massa lisa e divida em bolinhas.</li><li>Abra cada bolinha bem fina com as mãos ou um copo.</li><li>Asse em frigideira quente e seca, virando até dourar dos dois lados.</li></ol>",
        "publicar": 1,
        "data_criacao": 1782247889803,
        "data_atualizacao": 1782247889803,
        "e_favorito": 0
    },
    {
        "id": 17,
        "id_remoto": null,
        "titulo": "Macarrão Instantâneo Reforçado",
        "categoria": "🍝",
        "ingredientes": "<ul><li>1 pacote de macarrão instantâneo</li><li>1/2 lata de sardinha, atum ou salsicha picada</li><li>2 colheres (sopa) de milho ou ervilha em lata</li><li>Temperos do pacote a gosto</li></ul>",
        "instrucoes": "<ol><li>Cozinhe o macarrão na quantidade mínima de água necessária.</li><li>Acrescente a proteína em lata e os legumes escorridos.</li><li>Misture o tempero e aqueça por mais 1 minuto.</li><li>Sirva com pouco caldo para aproveitar todos os nutrientes.</li></ol>",
        "publicar": 1,
        "data_criacao": 1782247889803,
        "data_atualizacao": 1782247889803,
        "e_favorito": 0
    },
    {
        "id": 18,
        "id_remoto": null,
        "titulo": "Pasta de Feijão Enlatado",
        "categoria": "🫘",
        "ingredientes": "<ul><li>1 lata (ou 1 xícara) de feijão cozido, escorrido</li><li>1 colher (sopa) de azeite ou óleo</li><li>1 dente de alho amassado (ou alho em pó)</li><li>Sal e pimenta a gosto</li></ul>",
        "instrucoes": "<ol><li>Amasse o feijão com um garfo até virar uma pasta grossa.</li><li>Misture o azeite, o alho e os temperos.</li><li>Ajuste a consistência com um pouco de água, se necessário.</li><li>Sirva sobre pão, torradas ou bolachas.</li></ol>",
        "publicar": 1,
        "data_criacao": 1782247889803,
        "data_atualizacao": 1782247889803,
        "e_favorito": 0
    },
    {
        "id": 19,
        "id_remoto": null,
        "titulo": "Mistura Energética de Trilha",
        "categoria": "🥜",
        "ingredientes": "<ul><li>1 xícara de amendoim ou castanhas</li><li>1/2 xícara de uvas-passas ou frutas secas</li><li>1/2 xícara de aveia em flocos ou granola</li><li>2 colheres (sopa) de gotas de chocolate (opcional)</li></ul>",
        "instrucoes": "<ol><li>Misture todos os ingredientes em um pote bem fechado.</li><li>Guarde em local seco e fresco.</li><li>Consuma punhados ao longo do dia para repor energia.</li><li>Dura semanas sem refrigeração — ideal para a mochila de emergência.</li></ol>",
        "publicar": 1,
        "data_criacao": 1782247889803,
        "data_atualizacao": 1782247889803,
        "e_favorito": 0
    },
    {
        "id": 20,
        "id_remoto": null,
        "titulo": "Arroz com Lentilha de Uma Panela",
        "categoria": "🍚",
        "ingredientes": "<ul><li>1 xícara de arroz</li><li>1/2 xícara de lentilha</li><li>3 xícaras de água</li><li>1 colher (sopa) de óleo, sal e tempero a gosto</li></ul>",
        "instrucoes": "<ol><li>Lave o arroz e a lentilha juntos.</li><li>Leve ao fogo com a água, o óleo e o sal.</li><li>Cozinhe em fogo baixo e tampado até secar a água.</li><li>Descanse 5 minutos antes de servir; rende uma refeição completa.</li></ol>",
        "publicar": 1,
        "data_criacao": 1782247889803,
        "data_atualizacao": 1782247889803,
        "e_favorito": 0
    },
    {
        "id": 21,
        "id_remoto": null,
        "titulo": "Banana com Pasta de Amendoim",
        "categoria": "🍌",
        "ingredientes": "<ul><li>1 banana</li><li>1 a 2 colheres (sopa) de pasta de amendoim</li><li>Aveia ou granola para polvilhar (opcional)</li></ul>",
        "instrucoes": "<ol><li>Descasque e corte a banana ao meio no comprimento.</li><li>Espalhe a pasta de amendoim por cima.</li><li>Polvilhe aveia ou granola, se tiver.</li><li>Lanche rápido, calórico e sem cozimento.</li></ol>",
        "publicar": 1,
        "data_criacao": 1782247889803,
        "data_atualizacao": 1782247889803,
        "e_favorito": 0
    },
    {
        "id": 22,
        "id_remoto": null,
        "titulo": "Leite em Pó com Café",
        "categoria": "☕",
        "ingredientes": "<ul><li>3 colheres (sopa) de leite em pó</li><li>1 colher (chá) de café solúvel</li><li>1 xícara de água quente</li><li>Açúcar a gosto</li></ul>",
        "instrucoes": "<ol><li>Dissolva o leite em pó em um pouco de água fria para não empelotar.</li><li>Acrescente o café solúvel e o açúcar.</li><li>Complete com a água quente e misture bem.</li><li>Bebida reconfortante feita só com itens não perecíveis.</li></ol>",
        "publicar": 1,
        "data_criacao": 1782247889803,
        "data_atualizacao": 1782247889803,
        "e_favorito": 0
    },
    {
        "id": 23,
        "id_remoto": null,
        "titulo": "Batatas Assadas na Brasa",
        "categoria": "🥔",
        "ingredientes": "<ul><li>4 batatas médias com casca</li><li>Sal a gosto</li><li>Papel-alumínio (se houver)</li></ul>",
        "instrucoes": "<ol><li>Lave bem as batatas e fure-as com um garfo.</li><li>Embrulhe em papel-alumínio ou coloque direto na brasa.</li><li>Asse na fogueira por 30 a 45 minutos, virando de vez em quando.</li><li>Verifique o ponto com um palito; tempere com sal e sirva.</li></ol>",
        "publicar": 1,
        "data_criacao": 1782247889803,
        "data_atualizacao": 1782247889803,
        "e_favorito": 0
    },
    {
        "id": 24,
        "id_remoto": null,
        "titulo": "Sopa de Legumes em Lata Fortificada",
        "categoria": "🥫",
        "ingredientes": "<ul><li>1 lata de sopa ou de legumes (ervilha, milho, seleta)</li><li>1 lata de feijão ou grão-de-bico, escorrido</li><li>1 xícara de água</li><li>Sal, pimenta e azeite a gosto</li></ul>",
        "instrucoes": "<ol><li>Junte a sopa, os legumes e o feijão em uma panela.</li><li>Adicione a água e aqueça mexendo de vez em quando.</li><li>Tempere a gosto e finalize com um fio de azeite.</li><li>Refeição quente e nutritiva pronta em poucos minutos.</li></ol>",
        "publicar": 1,
        "data_criacao": 1782247889803,
        "data_atualizacao": 1782247889803,
        "e_favorito": 0
    }
]